pyndows/__init__.py
pyndows/_exceptions.py
pyndows/_windows.py
pyndows/testing.py
pyndows/version.py
pyndows-4.2.1.dist-info/LICENSE
pyndows-4.2.1.dist-info/METADATA
pyndows-4.2.1.dist-info/WHEEL
pyndows-4.2.1.dist-info/top_level.txt
pyndows-4.2.1.dist-info/RECORD
