Metadata-Version: 2.1
Name: pyndows
Version: 4.2.1
Summary: Accessing Windows from Linux
Home-page: https://colin-b.github.io/pyndows/
Author: Colin Bounouar
Author-email: colin.bounouar.dev@gmail.com
Maintainer: Colin Bounouar
Maintainer-email: colin.bounouar.dev@gmail.com
License: MIT
Download-URL: https://pypi.org/project/pyndows/
Project-URL: GitHub, https://github.com/Colin-b/pyndows
Project-URL: Changelog, https://github.com/Colin-b/pyndows/blob/master/CHANGELOG.md
Project-URL: Issues, https://github.com/Colin-b/pyndows/issues
Keywords: windows,samba,linux,remote
Platform: Windows
Platform: Linux
Classifier: Development Status :: 5 - Production/Stable
Classifier: Intended Audience :: Developers
Classifier: License :: OSI Approved :: MIT License
Classifier: Natural Language :: English
Classifier: Programming Language :: Python
Classifier: Programming Language :: Python :: 3
Classifier: Programming Language :: Python :: 3.6
Classifier: Programming Language :: Python :: 3.7
Classifier: Programming Language :: Python :: 3.8
Classifier: Topic :: Software Development :: Build Tools
Requires-Python: >=3.6
Requires-Dist: pysmb (==1.*)
Provides-Extra: testing
Requires-Dist: pytest-cov (==2.*) ; extra == 'testing'
